passagemath_modules/__init__.py
passagemath_modules-10.6.47.dist-info/DELVEWHEEL
passagemath_modules-10.6.47.dist-info/METADATA
passagemath_modules-10.6.47.dist-info/RECORD
passagemath_modules-10.6.47.dist-info/top_level.txt
passagemath_modules-10.6.47.dist-info/WHEEL
passagemath_modules.libs/libgcc_s_seh-1-8ac28fe21ad5783af7630f2f0c8f554d.dll
passagemath_modules.libs/libgmp-10-6a8fe126122672a8aed2558e30454e74.dll
passagemath_modules.libs/libgsl-28-269b4100f1097176f6de6feb5cf542c1.dll
passagemath_modules.libs/libgslcblas-0-71e420c446dd15a919acc7ca66677c13.dll
passagemath_modules.libs/libmpc-3-7c36a856a38a0face950aebc599843ce.dll
passagemath_modules.libs/libmpfr-6-49ffca41b058b2361798e7868a6ca7bf.dll
passagemath_modules.libs/libwinpthread-1-e271f374468d584905afcdf7da96a6ad.dll
passagemath_modules.libs/msvcp140-a4c2229bdc2a2a630acdc095b4d86008.dll
sage/all__sagemath_modules.py
sage/algebras/all__sagemath_modules.py
sage/algebras/catalog.py
sage/algebras/clifford_algebra.py
sage/algebras/clifford_algebra_element.cp311-win_amd64.pyd
sage/algebras/clifford_algebra_element.pxd
sage/algebras/clifford_algebra_element.pyx
sage/algebras/commutative_dga.py
sage/algebras/exterior_algebra_groebner.cp311-win_amd64.pyd
sage/algebras/exterior_algebra_groebner.pxd
sage/algebras/exterior_algebra_groebner.pyx
sage/algebras/finite_gca.py
sage/algebras/group_algebra.py
sage/algebras/octonion_algebra.cp311-win_amd64.pyd
sage/algebras/octonion_algebra.pxd
sage/algebras/octonion_algebra.pyx
sage/algebras/orlik_solomon.py
sage/algebras/orlik_terao.py
sage/algebras/weyl_algebra.py
sage/algebras/finite_dimensional_algebras/all.py
sage/algebras/finite_dimensional_algebras/finite_dimensional_algebra.py
sage/algebras/finite_dimensional_algebras/finite_dimensional_algebra_element.cp311-win_amd64.pyd
sage/algebras/finite_dimensional_algebras/finite_dimensional_algebra_element.pxd
sage/algebras/finite_dimensional_algebras/finite_dimensional_algebra_element.pyx
sage/algebras/finite_dimensional_algebras/finite_dimensional_algebra_ideal.py
sage/algebras/finite_dimensional_algebras/finite_dimensional_algebra_morphism.py
sage/algebras/lie_algebras/abelian.py
sage/algebras/lie_algebras/affine_lie_algebra.py
