Metadata-Version: 2.4
Name: passagemath-modules
Version: 10.6.47
Summary: passagemath: Vectors, matrices, tensors, vector spaces, affine spaces, modules and algebras, additive groups, quadratic forms, homology, coding theory, matroids
Author-email: The Sage Developers <sage-support@googlegroups.com>
Maintainer: Matthias Köppe, passagemath contributors
License-Expression: GPL-2.0-or-later
Project-URL: release notes, https://github.com/passagemath/passagemath/releases
Project-URL: repo (upstream), https://github.com/sagemath/sage
Project-URL: repo, https://github.com/passagemath/passagemath
Project-URL: documentation, https://passagemath.org/docs/latest
Project-URL: homepage (upstream), https://www.sagemath.org
Project-URL: discourse, https://passagemath.discourse.group
Project-URL: tracker (upstream), https://github.com/sagemath/sage/issues
Project-URL: tracker, https://github.com/passagemath/passagemath/issues
Classifier: Development Status :: 6 - Mature
Classifier: Intended Audience :: Education
Classifier: Intended Audience :: Science/Research
Classifier: Operating System :: POSIX
Classifier: Operating System :: POSIX :: Linux
Classifier: Operating System :: MacOS :: MacOS X
Classifier: Operating System :: Microsoft :: Windows
Classifier: Programming Language :: Python :: 3 :: Only
Classifier: Programming Language :: Python :: 3.10
Classifier: Programming Language :: Python :: 3.11
Classifier: Programming Language :: Python :: 3.12
Classifier: Programming Language :: Python :: 3.13
Classifier: Programming Language :: Python :: 3.14
Classifier: Programming Language :: Python :: Implementation :: CPython
Classifier: Topic :: Scientific/Engineering :: Mathematics
Requires-Python: <3.15,>=3.10
Requires-Dist: gmpy2~=2.1.b999
Requires-Dist: cysignals!=1.12.4; sys_platform == "win32"
Requires-Dist: cysignals!=1.12.0,>=1.11.2
Requires-Dist: memory_allocator
Requires-Dist: passagemath-categories~=10.6.47.0
Requires-Dist: passagemath-environment~=10.6.47.0
Requires-Dist: mpmath<1.4,>=1.1.0
Provides-Extra: test
Requires-Dist: passagemath-repl; extra == "test"
Provides-Extra: flint
Requires-Dist: passagemath-flint; extra == "flint"
Provides-Extra: fpylll
Requires-Dist: fpylll>=0.5.9; extra == "fpylll"
Provides-Extra: gsl
Provides-Extra: linbox
Requires-Dist: passagemath-linbox; extra == "linbox"
Provides-Extra: m4ri
Requires-Dist: passagemath-m4ri-m4rie~=10.6.47.0; extra == "m4ri"
Provides-Extra: m4rie
Requires-Dist: passagemath-modules[m4ri,pari]; extra == "m4rie"
Provides-Extra: meataxe
Requires-Dist: passagemath-meataxe; extra == "meataxe"
Provides-Extra: mpfi
Requires-Dist: passagemath-modules[flint]; extra == "mpfi"
Provides-Extra: mpfr
Provides-Extra: mpmath
Provides-Extra: ntl
Requires-Dist: passagemath-ntl; extra == "ntl"
Provides-Extra: numpy
Requires-Dist: numpy>=1.19; extra == "numpy"
Requires-Dist: numpy>=1.22.4; extra == "numpy"
Provides-Extra: pari
Requires-Dist: passagemath-pari; extra == "pari"
Provides-Extra: rdf
Requires-Dist: passagemath-modules[numpy]; extra == "rdf"
Provides-Extra: cdf
Requires-Dist: passagemath-modules[numpy]; extra == "cdf"
Provides-Extra: rr
Provides-Extra: cc
Provides-Extra: rif
Requires-Dist: passagemath-modules[flint]; extra == "rif"
Provides-Extra: cif
Requires-Dist: passagemath-modules[flint]; extra == "cif"
Provides-Extra: rbf
Requires-Dist: passagemath-modules[flint]; extra == "rbf"
Provides-Extra: cbf
Requires-Dist: passagemath-modules[flint]; extra == "cbf"
Provides-Extra: gf
Requires-Dist: passagemath-modules[pari]; extra == "gf"
Provides-Extra: gf2
Requires-Dist: passagemath-modules[m4ri]; extra == "gf2"
Provides-Extra: gf2e
Requires-Dist: passagemath-modules[m4rie]; extra == "gf2e"
Provides-Extra: gf2n
Requires-Dist: passagemath-modules[m4rie]; extra == "gf2n"
Provides-Extra: gfpn
Requires-Dist: passagemath-modules[meataxe]; extra == "gfpn"
Provides-Extra: qqbar
Requires-Dist: passagemath-modules[NumberField]; extra == "qqbar"
Provides-Extra: aa
Requires-Dist: passagemath-modules[NumberField]; extra == "aa"
Provides-Extra: ucf
Requires-Dist: passagemath-modules[gap]; extra == "ucf"
Provides-Extra: zp
Requires-Dist: passagemath-modules[pari]; extra == "zp"
Provides-Extra: qp
Requires-Dist: passagemath-modules[Zp]; extra == "qp"
Provides-Extra: zq
Requires-Dist: passagemath-modules[Zp]; extra == "zq"
Provides-Extra: qq
Requires-Dist: passagemath-modules[Zp]; extra == "qq"
Provides-Extra: finitefield
Requires-Dist: passagemath-modules[GF]; extra == "finitefield"
Provides-Extra: numberfield
Requires-Dist: passagemath-modules[flint]; extra == "numberfield"
Provides-Extra: quadraticfield
Requires-Dist: passagemath-modules[NumberField]; extra == "quadraticfield"
Provides-Extra: cyclotomicfield
Requires-Dist: passagemath-modules[NumberField]; extra == "cyclotomicfield"
Provides-Extra: padics
Requires-Dist: passagemath-modules[Zp]; extra == "padics"
Provides-Extra: standard
Requires-Dist: passagemath-modules[FiniteField,NumberField,combinat,flint,invariant,linbox,m4ri,m4rie,mpfi,ntl,numpy,padics,pari]; extra == "standard"
